LICENSE.txt
MANIFEST.in
requirements.txt
setup.py
phrase/__init__.py
phrase/corpus.py
phrase/create_phrase_dictionary_from_folder.py
phrase/noun_phrase_dictionary.py
phrase/phrase_dictionary.py
phrase/phrase_generation.py
phrase/tokenization.py
phrase/word_list.py
phrase.egg-info/PKG-INFO
phrase.egg-info/SOURCES.txt
phrase.egg-info/dependency_links.txt
phrase.egg-info/entry_points.txt
phrase.egg-info/requires.txt
phrase.egg-info/top_level.txt