Metadata-Version: 1.1
Name: phrase
Version: 0.0.9
Summary: Phrase: generates phrases given a corpus
Home-page: http://www.github.com/brentpayne/phrase
Author: Brent Payne
Author-email: brent.payne@gmail.com
License: UNKNOWN
Keywords: phrase,noun phrase,verb phrase,nlp,natural language processing,language,language processing,phrases,nltk
Platform: UNKNOWN
Classifier: Topic :: Text Processing :: General
Classifier: Topic :: Text Processing
Classifier: Programming Language :: Python
Classifier: Operating System :: OS Independent
Classifier: Intended Audience :: Developers
Classifier: License :: OSI Approved :: GNU Lesser General Public License v3 (LGPLv3)
